CHANGELOG.rst
COPYING
COPYING.LESSER
LICENSE
MANIFEST.in
README.rst
setup.py
ase_ext/__init__.py
ase_ext/lti_dos.py
ase_ext/monkey.py
ase_ext/test_lti_dos.py
ase_ext/utils.py
ase_ext.egg-info/PKG-INFO
ase_ext.egg-info/SOURCES.txt
ase_ext.egg-info/dependency_links.txt
ase_ext.egg-info/requires.txt
ase_ext.egg-info/top_level.txt
c/_ase_ext.c
c/_ase_ext.h
c/lti_dos.c